{
	"game": "The Elder Scrolls IV: Oblivion",
	"series": "The Elder Scrolls",
	"year": 2006,
	"status": "ready",
	"source": "https://www.mediafire.com/file/bhkqiqjhfib0waa/dialogueExport.txt/file",
	"sourceFeatures":{
		"type": "game data",
		"completeness": "complete",
		"dialogueOrder": false,
		"choices": "not included"
	},
	"notes": "See README",
    "error checks": {
        "truePositive_numTestsDone": "5",
        "truePositive_numParsingErrors": "0",
        "truePositive_numSourceErrors": "0",
        "truePositive_notes": "N/A",
    
        "falsePositive_numTestsDone": "5",
        "falsePositive_numErrors": "0",
        "falsePositive_notes": "N/A"
    },
	"parserParameters": {
		"parser":"OblivionParser",
		"fileType": ".txt"
	},
	"mainPlayerCharacters": [],
	"characterGroups": {
		"male": ["MQ15Orthe", "Suurootan", "AelwinMerowald", "AloysBincal", "HumilisNonius", "Wilbur", "NewheimthePortly", "DarkPrisonGuard06", "ScarTail", "UrielSeptim", "MQ06MythicDawnDoorkeeper", "LucienLachanceHunted", "Rindir", "DAHermaeusVoice", "OngartheWorldWeary", "ArenaRank1A", "DASheogorathVoice", "TertullianVerus", "MarinusCatiotus", "GogrongroBolmog", "SEKilibanNyrandil", "ThorleyAethelred", "MankarCamoran", "HelvoAtius", "SEMazaddha", "RisFralmoton", "SE09Victim03", "Cingor", "DANamiraPriest1", "JGhasta", "SEOrderPriest1", "DarkPirate2", "GinWulm", "Urjabhi", "Faelian", "Sshani", "Gogan", "Neville", "MS48OblivionSigilKeeper", "GerichSenarel", "Carandial", "StentheUgly", "MQ11ChorrolSoldier01", "SEJyggalagVoice", "MQ15MythicDawnLowM03", "SEArctus", "AdamusPhillida", "Wumeek", "FGGuardPorterSkingrad", "Tumindil", "Bongond", "BrusciusLongus", "MogensWindShifter", "UrbulgroOrkulg", "TorbaltheSufficient", "BWCWatersEdge1", "DarkPirate4", "EdgarVautrine", "StantusVarrid", "Hundolin", "Ocato", "Gwinas", "LurioMaenius", "Belisarius", "MQ10BrumaGuard01", "MQ11SkingradSoldier01", "AudensAvidius", "Rijirr", "Pranal", "BWCWatersEdge3", "Ribassa", "Srathad", "MelusPetilius", "Raqanar", "Langley", "KrognakgroBrok", "GramangroMarad", "NatchPinder", "Generic GoldenSaint Male", "TestToddManShield", "SE08DarkSeducer03", "SE01GateVoice1", "AvrusAdas", "HackdirtBrethrenMonster", "Othrelos", "DAClavicusVoice", "MariusCaro", "Rizakar", "MathieuBellamont", "ArentusFalvius", "MagubgraOrum", "OgierGeorick", "ForlornWatchmanPre", "RoliandHanus", "Thaurron", "AmminusGregori", "JesanSextius", "LuronkgroGlurzog", "SERanarrJo", "BugakgroBol", "DranasLlethro", "Jorundr", "DANamiraVoice", "JeetumZe", "EugalBelette", "SEJzidzoMania", "TestKenManOrc", "HenantierDream", "GhorubgroUgdub", "OtiusLoran", "Varnado", "SEShelden", "MQ05MythicDawnGuard01", "SEAmiableFanriene", "KantavCheynoslin", "HaulsRopesFaster", "VelanAndus", "BrielusGawey", "DarkPrisonGuard05", "Carsten", "DANamiraForgotten2", "HrolUlfgar", "DANamiraPriest2", "GrayFox", "DelosFandas", "SE09Victim02", "MenienGoneld", "Gilgondorin", "UlrichLeland", "TertiusFavonius", "PennusMallius", "Olfand", "SEBruscusDannus", "SEPrisoner1Syl", "LordRugdumph", "SEBeggarGloorolros", "GaturngroGonk", "E3KvatchStartSoldier", "OntusVanin", "DamianMagius", "NelsTheNaughty", "AymarDouar", "ErTeeusSOUL", "SE10Seducer", "SorisArenim", "Enrion", "Generic WoodElf Male", "DidierAumilie", "MQ15Kathutet", "ChorrolGuardCountess", "Caenlorn", "SEDyus", "MuggraMurgak", "Baenlin", "UurastheShepherd", "OlynSeran", "AgronakGroMalog", "DANamiraPriest4", "Teinaava", "SE32Reveler01", "Amir", "Lynch", "Rvanni", "HafidHollowleg", "FrancoisMotierre", "Dorian", "BeggarLeyawiinDeehTheScalawag", "BrotherPiner", "SEToveTheUnrestful", "SEPadEi", "IrlavJarol", "Enilroth", "TestKenManArgonian", "TrenusDuronius", "RavenCamoran", "MercatorHosidus", "JakbenImbel", "Glenroy", "SESheogorath", "MG16NecromancerMale2", "SalomonGeonette", "TunZeeus", "GanLuseph", "ValenDreth", "SEHillOfSuicidesGhost03", "ShumgroYarug", "DarkPirate6", "SEBelmyneDreleth", "MQ15MythicDawnPrisonerMale", "ViatorAccius", "Hlofgar", "MQ10BrumaGuard03", "Rhano", "MaroRufus", "KastusSintav", "Fjotreid", "SE11Apostle07", "Mishaxhi", "SE01GaiusPrentus", "Merandil", "MS49LegionSoldier", "GrayFoxCorvus", "ReistrtheRotted", "Ernest", "GorgogroShura", "Orrin", "SERavenBiter", "PriorMaborel", "SEUshnarGroShadborgob", "JaFazir", "Eitar", "SEHalion", "MarcGulitte", "MGMageApprentice6", "LutherBroad", "Denel", "Generic Sheogorath Male", "AncusAfranius", "MS94ImperialCaptain", "MQ09UndeadBlade03", "Hagaer", "Brodras", "SE32Fanatic4Boss", "Jbaana", "Delmar", "SE08DarkSeducer02", "AlgottheNortherner", "SE32VitharnPatriach", "BleakMineGuardCaptain2", "VelusHosidius", "MQ16Messenger", "PinarusInventius", "RytheLythandas", "DulfishgroOrum", "BrucetusFestinius", "ErTeeus", "LordLovidicus", "LordDrad", "ArenaICBlueTeamGladiator", "Ksharr", "HidesHisHeart", "UlfgarFogEye", "BWCWatersEdge2", "Ohtimbar", "Henantier", "MGMageApprentice10", "MQ06MythicDawnGuard", "Dion", "ErnestManis", "Maraska", "ToothintheSea", "SevariusAtius", "Regner", "Fithragaer", "Otumeel", "Merildor", "SE32Fanatic3", "DAPeryiteVoice", "MS11BrumaInvestigatorGuard02", "MQ13BrumaSoldier", "KurzgroBaroth", "Dark19Murderer1", "Generic Nord Male", "SEUrulGoAgamphMania", "AldosOthran", "ServatiusQuintilius", "Ruslan", "SEHorkvirBearArmDementia", "RimalusBruiant", "TestVendorNPC", "HiltheTall", "Thoronir", "MQ09UndeadBlade01", "SEGrommokgroBarak", "Arkved", "Olav", "MaknokgroCoblug", "Generic Redguard Male", "UzulGroGrulam", "Torbern", "testHEMale2", "VlanhonderMoslin", "DANamiraForgotten4", "FerulRavel", "Jskar", "Dark09PhillidaBodyguard", "MQ15MythicDawnLowM04", "TESTRedguard", "BolorSavel", "Falcar", "SavlianMatius", "MQ15MythicDawnLowM01", "Erthor", "Phintias", "RightWind", "RaJhan", "AlixLencolia", "VantusPrelius", "MQ11AnvilSoldier01", "SEHorkvirBearArmMania", "Jbari", "GuilbertJemane", "MQ05MythicDawnGuard02", "TrayvondtheRedguard", "ArmandChristophe", "Ancotar", "AntusOdiil", "FadusCalidius", "TestDenyiir", "ArenaRank6B", "Cirroc", "SEUrulGoAgamphDementia", "MGMageApprentice3", "MGMageApprentice9", "CorrickNorthwode", "SEGrommokgroBarakGhosted", "Harrow", "SEBeggarBhisha", "SEPyke", "Willet", "ArenaRank5E", "MS93Crewmember1", "Wallace", "DABarnasVoice", "AlbericLitte", "LeyawiinGuardCastleSanguine", "Anguilon", "DarkPrisonGuardTaunt", "SEBreakneckPatrol02", "MQ16PalaceGuard", "AhMalz", "Elidor", "RemanBroder", "OleedEi", "BremmanSenyan", "DanusArtellian", "Holger", "Seridur", "AntoineBranck", "SuriusAfranius", "BeggarBravilCosmusTheCheat", "Geel", "DiramSerethi", "SE10SaintMaleWarrior1", "Roliand", "Salmo", "Aenvir", "Mahei", "HillodTheOutlaw", "KeldoftheIsles", "CiceroVerus", "CylbenDolovas", "Lithnilian", "DrelsTheran", "ColinStedrine", "BettoPlotius", "DAMalacathVoice", "ArenaHopeful2", "Ungarion", "SE02OrcCaptain", "Droshanji", "JzinDar", "Logvaar", "KurdangroDragol", "Sdrassa", "GulGroBurbog", "SEDumagGraBonk", "SE08GoldenSaint02", "DeetumJa", "Generic Breton Male", "Generic Imperial Male", "GregoryArne", "LerexusCallidus", "BerichInian", "BasilErnarde", "SEOrinthal", "BazurgroGharz", "LorgrenBenirusNPC", "HieronymusLex", "FathisUles", "SulinusVassinus", "Cyrus", "GraklakgroBuglump", "TyrelliusLogellus", "DAMolagBalVoice", "StorntheBurly", "ShagolgroBumph", "SEBeggarFimmion", "Honditar", "SergiusVerus", "DecentiusOpsius", "DANamiraForgotten1", "Sinderion", "Generic Orc Male", "TESTNord", "Usheeja", "DarJee", "GarrusDarelliun", "AjumKajin", "Generic HighElf Male", "IlendVonius", "FathisAren", "WilhelmtheWorm", "DANamiraForgotten1b", "TimotheeLaRouche", "SEErverDevani", "VontusIdolus", "Volanaro", "IsleifTheOpenHanded", "Generic Dremora Male", "MatthiasDraconis", "CyroninSintav", "ValusOdiil", "SE11Apostle06", "GrayFoxStranger", "Burd", "RegulusTerentius", "ValandrusAbor", "NorbertLelles", "IlvelRomaynSOUL", "Pajeen", "AmbroiseCanne", "Jair", "Rufio", "NivanDalvilu", "SEBrithaur", "SE14VoiceofSheogorath", "FrancoisMotierreFaked", "HannibalTraven", "ValenDrethDark04", "DarkPirate3", "Teekeeus", "Maenlorn", "GelliusTerentius", "DarkPrisonGuard04", "SE32BatGroOrkul", "VelwynBenirus", "GuilbertSelone", "Thurindil", "ItiusHayn", "CastaFlavus", "GreyThroat", "Calindil", "Honmund", "ManheimMaulhand", "SEHaskill", "MraajDar", "MQ11KvatchSoldier01", "SE08GoldenSaint01", "SEFelasSarandas", "HeinrichOakenHull", "SE32DesideratusAnnius", "ArenaFan1", "MQ16ImperialCaptain01", "HastrelOttus", "DAHircineVoice", "SE11Rakheran", "ArenaMouth", "Martin", "DavideSurilie", "MQ15Eldamil", "SERendilDrarara", "AlvalUvani", "BittneldtheCurseBringer", "RaminusPolus", "Generic Argonian Male", "TyrelliusLogellusOffDuty", "BogrumGroGalash", "Larthjar", "SE32Anglor", "KastavKvinchal", "ReynaldJemane", "UlenAthram", "MQ13BrumaMilitiaMale", "SE32Fanatic2", "BleakMineGuardCaptain", "WormAnchorite", "SE08DarkSeducer01", "Foroch", "Rellian", "Generic DarkElf Male", "HansBlackNail", "DarkDoorSpeakNPC", "Baurion", "HelviusCecia", "SEYngvar", "GeemJasaiin", "HuntingTail", "SE08GoldenSaint03", "DranasLerano", "RalsaNethan", "SEBigHead", "VontanSintav", "Daenlin", "MS94ImperialSoldier", "FarwilIndarys", "SEKithlan", "BelisariusArius", "DarkPrisonGuard02", "CatFace", "Mannimarco", "Hirtel", "Jauffre", "RodericPierrane", "RenaldViernis", "Errandil", "Sakeepa", "Gromm", "SEBeggarUungor", "SE08GoldenSaint04", "DABoethiaVoice", "Ungolim", "Steffan", "ModrynOreyn", "JanusHassildor", "TovasSelvani", "ClaudeMaric", "SERelan", "Athragar", "Arterion", "SamuelBantien", "ClaudiusArcadia", "IlvelRomayn", "BleakMineGuard", "Generic DarkSeducer Male", "Dark19Murderer3", "MelsMaryon", "SE12OrderPriestMania1", "Ormil", "AzaniBlackheart", "ViranusDonton", "testHEMale", "ArenaRank3A", "MondrarHenim", "Generic Khajiit Male", "E3KvatchCaptain01", "WeebumNa", "EduardRetiene", "SnartheCook", "DASanguineVoice", "SE32VitharnSoldier01", "SEHirrusClutumnus", "Styrbjorn", "SE32Fanatic1", "MarcelAmelion", "Gelephor", "RufriusVinicius", "ShobobgroRugdush", "MagragroNaybek", "Ortis", "SEEaril", "Azzan", "SEJzidzoDementia", "BeggarCheydinhalBrucciusTheOrphan", "Hassiri", "LeyMarillin", "SEBeggarBolwing", "ChristopheMarane", "Generic VampireRace Male", "AndreasDraconis", "GastonTussaud", "Kalthar", "DreetLai", "Iver", "Amusei", "SE32HlovalDreth", "MGMageApprentice7", "Voranil", "IrroketheWide", "Demetrius", "OrgnolfHairyLegs", "Tilmo", "Haekwon", "VaronVamori", "GilenNorvalo", "VlanarusKvinchal", "PrimoAntonius", "Rajiradh", "FelenRelas", "JanuariusAurunceia", "Winson", "RaynilDralas", "Baeralorn", "LaytheWavrick", "Hjar", "SEHerdir", "ToutiusSextius", "DANamiraPriest3", "Aengvir", "SE08DarkSeducer04", "Beirir", "AmantiusAllectus", "Areldil", "SE11ApostleTraitor02", "SELewinTilwald", "SEDervenin", "GasparStegine", "MGMageScholar", "InielSintav", "MGMageApprentice2", "Srazirr", "Gunder", "BrotchCalus", "MQ09UndeadBlade04", "ShadySam", "VarelMorvayn", "MGMageApprentice5", "TESTArgonian", "Agarmir", "ArenaRank2A", "JBaasha", "BarthelGernand", "Tolgan", "MS13CheydinhalGuardB", "GureryneSelvilo", "AndelIndarys", "Owyn", "OrokgroGhoth", "Umbacano", "ArenaRank3C", "Angalmo", "SE10SeducerMaleWarrior1", "Gundalas", "SE12OrderPriestDementia1", "SEOrderPriest2", "MQ09UndeadBlade02", "LazareMilvan", "DovynAren", "MQ10BrumaGuard02", "RallusOdiil", "Wrath", "DubokgroShagk", "MalintusAncrus", "Jeelius", "Athrelor", "MQ11LeyawiinSoldier01", "CariusRunellius", "Maglir", "JesanRilian", "SEDulphumphGroUrgash", "Glarthir", "Kewan", "MQ15MythicDawnXivCatcher", "AleronLoche", "DarkPrisonGuard03", "GastonSurilie", "Engorm", "Boldon", "SEMirel", "MQ05AstavWirich", "KewanSOUL", "Caenlin", "CGMythicDawnAssassinFinal", "GranthamBlakeley", "Borissean", "Eridor", "DulgroShug", "LumgroBaroth", "SEJayredIceVeins", "BeranSintav", "Baurus", "Jmhad", "Jollring", "Curtis", "Shameer", "Shamar", "ViggetheCautious", "Eronor", "Fafnir", "SEGundlar", "ContumeliorusFlorius", "JivHiriel", "SE11ApostleTraitor01", "SE32CountCirion", "MS10CheydinhalHouseGuard01", "TestKenManKhajiit", "DarkPirate1", "SESyndeliusGatharian", "SEThadon", "BrokilgroShatur", "FGGuardPorterLeyawiin", "Orintur", "BurzGroKhash", "UlmuggroCromgog", "LucienLachance", "RolandJenseric", "BragGroBharg", "JharedStrongblade", "GemellusAxius", "IlavDralgoner", "Maiqtheliar", "VicenteValtieri", "GoganGuard", "Hridi", "BanusAlor"], 
		"female": ["NoveniOthran", "Alga", "Eilonwy", "Jensine", "SESontaire", "SESfara", "DAMeridiaVoice", "SignyHomeWrecker", "RestitaStatlilia", "SE14Healer1", "Dark19Murderer2", "OlavatheFair", "Skaleel", "CitySwimmer", "CarmanaSintav", "Generic Imperial Female", "RosentiaGallenus", "Shamada", "MargueriteDiel", "ChanaMona", "EtiraMoslin", "SETilseAreleth", "GruiandGarrana", "IdaVlinorman", "SERunsInCircles", "Shafaye", "DAAzuraVoice", "Palonirya", "Tsrava", "Andragil", "SchlerusSestius", "RogmeshgraCoblug", "Trevaia", "MarentheSeal", "SEUlfri", "MatildePetit", "Tandilwe", "MazogatheOrc", "JantusBrolus", "BumphgraGash", "ElseGodHater", "Nilawen", "MS93Varulae", "Bejeen", "BralsaAndaren", "SEBrevi", "SEAdeo", "Melisande", "JeanneFrasoric", "SEDredhwen", "Chanel", "CaeliaDraconis", "SE13DarkSeducerMessenger", "SEJastiraNanusDementia", "BieneAmelion", "Ohtesse", "SEDarkSeducerGuardPost", "Caminalda", "Merete", "LlensiLlaram", "Ganredhel", "HomrazgraMorgrump", "LadyRogbut", "Sthasa", "MoggraMogakh", "DANamiraForgotten4a", "NarinaCarvain", "Minerva", "Emfrid", "Sigrid", "OraggraBargol", "Degil", "Atraena", "MarlenaBrussiner", "SEAtrabhiMania", "Jearl", "PistaMarillin", "Sjirra", "DarkFirstMate", "MGMageApprentice8", "TanasaArano", "SEWideEye", "Nardhil", "IsabeauBienne", "SE14DSEscort", "Tavia", "Telaendril", "BlancheMastien", "PraxedesAfranius", "DAVaerminaVoice", "Faurinthil", "Generic WoodElf Female", "lyndacartertest", "Rasheda", "Dremora5MarkynazMissile3", "Numeen", "Witseidutsei", "RonaHassildor", "ClaudettePerrick", "HalLiurz", "SE14Dancer1", "Marz", "JavoliaMaborel", "SnakgraBura", "Uurwen", "ErinaJeranus", "Dagail", "MarietteRielle", "Skasha", "NorasaAdus", "IsaRaman", "Shelley", "UravasaOthrelas", "Karinnarre", "SEThaedil", "TadroseHelas", "Neesha", "Umbra", "AlessiaOttus", "MQ15MythicDawnPrisonerFemale", "Selene", "MariePalielle", "DelphineJend", "Kiara", "DumaniaJirich", "SENanetteDon", "MaelonaGuard", "SEAtrabhiDementia", "DAMephalaVoice", "Ayisha", "DovesiDran", "MartinaFloria", "CandiceCorgine", "Shomara", "Bothiel", "Ranaline", "Arquen", "Oleta", "DANamiraForgotten3b", "BronsilaKvinchal", "SEMuurine", "Agata", "Parwen", "JulittaPlotius", "SE11Ciirta", "Yushi", "AlvesUvenim", "ArenaRank4C", "BorbagraUzgash", "DraranaThelis", "Thalfin", "MaranaRian", "MivrynaArano", "ArenaRank5B", "Generic Khajiit Female", "BeatriceGene", "Nerussa", "SE13DarkSeducerCaptain", "TarMeena", "Angelie", "SECindanwe", "Rona", "OghashgraMagul", "LlevanaNedaren", "SE13GoldenSaintPlayer", "TivelaLythandas", "SisterAngrond", "ErissareArenim", "BernadettePeneles", "SEDylora", "SilanaBlandia", "Elsynia", "Ruma", "MaevatheBuxom", "Deetsan", "Malene", "SelenaOrania", "Generic HighElf Female", "Maelona", "MirieSOUL", "MarentheSealSOUL", "ArenaRank2B", "SE08DarkSeducerGrakendoUdico", "AntoinettaMarie", "IreneMetrick", "Courier3", "FaustinaCartia", "Rigmor", "RoxanneBrigette", "Generic DarkSeducer Female", "SE06GoldenSaintWarden", "SE14GSEscort", "SESheerMeedish", "AvieraNirol", "Ahdarji", "SECaldanaMonrius", "Generic Breton Female", "UgakgraMogakh", "YsabelAndronicus", "DarMa", "WeedumJa", "SE13DarkSeducerPlayer", "Carahil", "Smirra", "Ashni", "BeggarBravilWretchedAia", "SETallTreesFalling", "MirabelleMonet", "Alawen", "Skrivva", "Atahba", "Aryarie", "TG03ChapelUnderCroftGuard", "Zahrasha", "SEKishashi", "AdrienneBerene", "RomanaFaleria", "JenaSintav", "TheNightMother", "SECutter", "SE07ASESylDouble", "CalliaBincal", "SE13GoldenSaintCaptain", "SE07BGoldenSaintGardenGuard", "OnStayaSundew", "MyvrynaArano", "Thamriel", "SE13GoldenSaintMessenger", "SEMiriliUlven", "Boroneth", "Astante", "DroNahrah", "HlidaraMothril", "DavelaHlaren", "SE06DarkSeducerWarden", "SEStela", "Hasathil", "Elragail", "ElisaPierrane", "DANocturnalVoice", "DynariAmnis", "KudEi", "SEStaada", "Ocheeva", "Abhuki", "SE32VitharnMatriach", "BeggarCheydinhalLucklessLucina", "QuillWeave", "Generic Nord Female", "AdosiSerethi", "HjolfroditheHarrier", "Vajhira", "ViniciaMelissaeia", "Generic Dremora Female", "SEBrellachGuard", "MGMageApprentice", "Generic DarkElf Female", "SEPinnacleRockGuard", "SE14Juggler", "UrnsiSerethi", "NaspiaCosma", "Ashanta", "TertiaViducia", "ArnoraAuria", "JastiaSintav", "CastaScribonia", "Dairihill", "SE32Althel", "Rana", "Skjorta", "LadyDrad", "SEIssmi", "BeggarLeyawiinRancidRadirsha", "ElanteofAlinor", "Mirie", "UrsanneLoche", "AugustaCalidia", "Isolde", "Generic GoldenSaint Female", "ArvenaThelas", "SENelrene", "Minx", "MensaSelas", "DraloraAthram", "MQ11CheydinhalSoldier01", "SERelmynaVerenim", "Tierra", "UndenaOrethi", "DredenaHlavel", "MQ13BrumaMilitiaFemale", "LucianaGalena", "FalanuHlaalu", "RenaBruiant", "Carwen", "EdlaDarkHeart", "Tsavi", "SEBeelei", "Mirisa", "BatulgraSharob", "SisterPhebeJeanard", "MarianaAncharia", "Dhola", "Methredhel", "JanoniaAurunceia", "Eyja", "Generic Argonian Female", "AstiniaAtius", "SE09Victim01", "JulienneFanis", "MGMageApprentice4", "Caranya", "SESyl", "CaulaAllectus", "UlrikaUlfgar", "HerminiaCinna", "TolisiGirith", "YvaraChannitte", "Vigdis", "Laralthir", "IdaOttus", "Generic Redguard Female", "MorGraGamorn", "EstelleRenoit", "MachNa", "MQ15MythicDawnLowF01", "ArenaHopeful1", "MG16NecromancerFemale2", "Glistel", "SEJastiraNanusMania", "SEKaneh", "ItaRienus", "SEAhjazda", "Sherina", "SESicklyBernice", "Nahsi", "Beewos", "DANamiraForgotten2a", "Angalsama", "SE10SaintWarrior1", "MQ15MythicDawnLowF02", "RochelleBantien", "AlessiaCaro", "VieraLerus", "DANamiraForgotten1a", "ArrianaValga", "SeedNeeus", "Ciindil", "SE08GoldenSaintAurigDesha", "ErlineLirrian", "Eletta", "TG06PaleLadyVampire", "ArenaICYellowTeamChampion", "TolvasaSendas", "Ardaline", "RalsaNorvalo", "Rohssan", "SE07BGoldenSaintPalaceGuard", "MillonaUmbranox", "DerveraRomalen", "ArenaRank6E", "Druja", "Jena", "SE04FelldewAddict01", "BoderiFarano", "Tamika", "Talasma", "UleneHlervu", "Generic Orc Female", "ReneeGeonette", "Petrine", "SEZoeMalene", "Margarte", "ArielleJurard", "Rienna", "PerenniaDraconis", "Adanrel", "Anedhel", "SEUnaArmina", "FrancineVelain", "CamillaLollia", "Clesa", "Earana", "Tenville", "VilenaDonton", "LenkaValus", "RusiaBradus", "SE10Saint", "BurMeema", "AstiaInventius", "SEAnyaHerrick", "CarmenLitte", "SabineLaul", "Caroline", "UmoggraMarad", "Renote", "Huurwen", "Shuravi", "Mandil", "AgnetethePickled"],
		"GenericMale": ["Generic Breton Male", "Generic DarkElf Male", "Generic DarkSeducer Male", "Generic Dremora Male", "Generic GoldenSaint Male", "Generic HighElf Male", "Generic Imperial Male", "Generic Khajiit Male", "Generic Nord Male", "Generic Orc Male", "Generic Redguard Male", "Generic Sheogorath Male", "Generic VampireRace Male", "Generic WoodElf Male"],
		"GenericFemale": ["Generic Argonian Female", "Generic Breton Female", "Generic DarkElf Female", "Generic DarkSeducer Female", "Generic Dremora Female", "Generic GoldenSaint Female", "Generic HighElf Female", "Generic Imperial Female", "Generic Khajiit Female", "Generic Nord Female", "Generic Orc Female", "Generic Redguard Female", "Generic WoodElf Female"]
	},
	"aliases": {
	}
}
